MANIFEST.in
README.rst
setup.py
django_shareable/__init__.py
django_shareable/models.py
django_shareable/views.py
django_shareable.egg-info/PKG-INFO
django_shareable.egg-info/SOURCES.txt
django_shareable.egg-info/dependency_links.txt
django_shareable.egg-info/not-zip-safe
django_shareable.egg-info/requires.txt
django_shareable.egg-info/top_level.txt
django_shareable/static/django_social_share/css/styles.css
django_shareable/static/django_social_share/i/facebook.png
django_shareable/static/django_social_share/i/twitter.gif
django_shareable/templates/django_shareable/templatetags/post_to_facebook.html
django_shareable/templates/django_shareable/templatetags/post_to_twitter.html
django_shareable/templatetags/__init__.py
django_shareable/templatetags/social_share.py