Metadata-Version: 1.1
Name: django-shareable
Version: 0.2.7
Summary: Templatetags for 'tweet this' and 'share on facebook'
Home-page: https://github.com/chrisspen/django-shareable
Author: Chris Spencer
Author-email: chrisspen@gmail.com
License: MIT
Platform: UNKNOWN
Classifier: Development Status :: 3 - Alpha
Classifier: Environment :: Web Environment
Classifier: Intended Audience :: Developers
Classifier: License :: OSI Approved :: MIT License
Classifier: Operating System :: OS Independent
Classifier: Programming Language :: Python
Classifier: Framework :: Django
